just_use_dataclass/__init__.py
just_use_dataclass/converter.py
just_use_dataclass-0.1.1.dist-info/LICENSE
just_use_dataclass-0.1.1.dist-info/METADATA
just_use_dataclass-0.1.1.dist-info/WHEEL
just_use_dataclass-0.1.1.dist-info/RECORD
