Metadata-Version: 2.1
Name: just-use-dataclass
Version: 0.1.1
Summary: Convert a python dictionary into a dataclass
License: MIT
Author: André da Silva
Author-email: andre-da.silva@outlook.com
Requires-Python: >=3.9,<4.0
Classifier: License :: OSI Approved :: MIT License
Classifier: Programming Language :: Python :: 3
Classifier: Programming Language :: Python :: 3.9
Classifier: Programming Language :: Python :: 3.10
Classifier: Programming Language :: Python :: 3.11
